robust_downloader/__init__.py
robust_downloader/cli.py
robust_downloader/constants.py
robust_downloader/downloader.py
robust_downloader/utils.py
robust_downloader/providers/gdrive.py
robust_downloader/providers/s3.py
robust_downloader-0.0.1.dist-info/LICENSE.md
robust_downloader-0.0.1.dist-info/METADATA
robust_downloader-0.0.1.dist-info/WHEEL
robust_downloader-0.0.1.dist-info/entry_points.txt
robust_downloader-0.0.1.dist-info/top_level.txt
robust_downloader-0.0.1.dist-info/RECORD
